fourierplotter/__init__.py
fourierplotter/__main__.py
fourierplotter/fourier_solver.py
fourierplotter/plotter.py
fourierplotter/svg_to_pts.py
fourierplotter-0.0.1.dist-info/LICENSE
fourierplotter-0.0.1.dist-info/METADATA
fourierplotter-0.0.1.dist-info/WHEEL
fourierplotter-0.0.1.dist-info/entry_points.txt
fourierplotter-0.0.1.dist-info/top_level.txt
fourierplotter-0.0.1.dist-info/RECORD
