Metadata-Version: 2.1
Name: fourierplotter
Version: 0.0.1
Summary: Use complex Fourier Analysis to draw svg images
Home-page: https://github.com/ianre657/FourierPlotter
Author: Ian Chen
Author-email: ianre657@gmail.com
License: UNKNOWN
Platform: UNKNOWN
Classifier: Programming Language :: Python :: 3
Classifier: License :: OSI Approved :: MIT License
Classifier: Operating System :: OS Independent
Requires-Python: >=3.6
